fangfrisch/__init__.py
fangfrisch/__main__.py
fangfrisch/db.py
fangfrisch/download.py
fangfrisch/dump.py
fangfrisch/log.py
fangfrisch/refresh.py
fangfrisch/task.py
fangfrisch/util.py
fangfrisch/config/__init__.py
fangfrisch/config/config.py
fangfrisch/config/fangfrischnews.py
fangfrisch/config/interserver.py
fangfrisch/config/malwarepatrol.py
fangfrisch/config/sanesecurity.py
fangfrisch/config/securiteinfo.py
fangfrisch/config/urlhaus.py
fangfrisch-1.9.2.dist-info/licenses/LICENSE
fangfrisch-1.9.2.dist-info/METADATA
fangfrisch-1.9.2.dist-info/WHEEL
fangfrisch-1.9.2.dist-info/entry_points.txt
fangfrisch-1.9.2.dist-info/top_level.txt
fangfrisch-1.9.2.dist-info/RECORD
