Metadata-Version: 2.4
Name: fangfrisch
Version: 1.9.2
Summary: Update and verify unofficial Clam Anti-Virus signatures
Author-email: Ralph Seichter <fangfrisch@seichter.de>
Project-URL: Documentation, https://rseichter.github.io/fangfrisch/
Project-URL: Source, https://github.com/rseichter/fangfrisch
Project-URL: Issues, https://github.com/rseichter/fangfrisch/issues
Keywords: antivirus,clamav,freshclam,refresh,update
Classifier: Development Status :: 6 - Mature
Classifier: Intended Audience :: System Administrators
Classifier: License :: OSI Approved :: GNU General Public License v3 or later (GPLv3+)
Classifier: Operating System :: OS Independent
Classifier: Programming Language :: Python :: 3.9
Classifier: Topic :: System :: Systems Administration
Classifier: Topic :: Utilities
Requires-Python: >=3.9
License-File: LICENSE
Requires-Dist: requests>=2.22.0
Requires-Dist: SQLAlchemy>=1.4.0
Dynamic: license-file
